{"type":"doc","filename":"guide-file-structure.asciidoc.html","anchor":"guide-file-structure.asciidoc_toplevel","title":"Toplevel","breadcrumbs":["Angular","Angular","File Structure"],"text":"Toplevel\n\nThe toplevel file structure is defined by Angular CLI. You might put this \"toplevel file structure\" into a subdirectory to facilitate your build, but this is not relevant for this guide. So the applications file structure relevant to this guide is the folder /src/app inside the part managed by Angular CLI.\n\n\nListing 66. Toplevel file structure shows feature modules\n\n\n\n\n\nBesides the definition of app module the app folder has feature modules on toplevel.\nThe special modules shared and core are present as well.\n\n\n\n"}