{"type":"doc","filename":"guide-structure-modern.asciidoc.html","anchor":"guide-structure-modern.asciidoc_modules","title":"Modules","breadcrumbs":["Java","Quarkus","Modern project structure"],"text":"Modules\n\nDue to trends such as microservices, we are building smaller apps compared to moduliths.\nFor simplicity, we therefore do not split our app into different modules and keep everything top-level and easy.\n\n\nIn addition to java and resources, we also add helm for helm templates and docker for docker scripts (e.g. Dockerfile) in src/main:\n\n\n\n\n\n\n\n\n"}