{"type":"doc","filename":"nkaas.asciidoc.html","anchor":"nkaas.asciidoc","title":" on Native Kubernetes as a Service (nKaaS)","breadcrumbs":["MyThaiStar","CI/CD","<code>MyThaiStar</code> on Native Kubernetes as a Service (nKaaS)"],"text":"MyThaiStar on Native Kubernetes as a Service (nKaaS)\n\nThe MyThaiStar sample application can be deployed on a nKaaS environment. The required Kubernetes configuration files can be found in the MyThaiStar repository. There are no additional changes required in order to deploy the application.\n\n\n"}