{"type":"doc","filename":"devonfw-guide_solicitor.wiki_master-solicitor.asciidoc_reporting-templates.html","anchor":"devonfw-guide_solicitor.wiki_master-solicitor.asciidoc_attributions.vm","title":"Attributions.vm","breadcrumbs":["Tools","Solicitor User Guide","Appendix C: Reporting Templates"],"text":"Attributions.vm\n\nThis template creates an attributions document which lists all used OSS components with their licenses, license texts and found copyrights information as well as found information from NOTICE files.\nThe template is part of the Experimental Scancode Integration and requires ScanCode to be used to collect all necessary information.\n\n\n\n\n"}