{"type":"doc","filename":"devonfw-guide_ide.wiki_advanced-tooling-generic.asciidoc.html","anchor":"devonfw-guide_ide.wiki_advanced-tooling-generic.asciidoc_browser-plugins","title":"Browser Plugins","breadcrumbs":["devonfw-ide","Advanced Features","Cross-Platform Tooling"],"text":"Browser Plugins\n\nThere are tons of helpful browser plugins out there and it might be a matter of personal taste what you like to have installed. However, as we are heavily using github we want to promote octotree.\nIn case you also work with ZenHub you might want to install the Zenhub Browser Extension.\n\n\n\n\n\n"}