{"type":"doc","filename":"devonfw-guide_devon4net.wiki_templates.asciidoc.html","anchor":"devonfw-guide_devon4net.wiki_templates.asciidoc_net-core-3.0","title":"Net Core 3.0","breadcrumbs":[".net","Templates","Templates"],"text":"Net Core 3.0\n\nThe .Net Core 3.0 template allows you to start developing an n-layer server application to provide the latest features. The template can be used in Visual Studio Code and Visual Studio 2019.\n\n\nThe application result can be deployed as a console application, microservice or web page.\n\n\nTo start developing with devon4Net template, please follow this instructions:\n\n\nUsing devon4Net template\n\n\n\nOption 1\n\n\n\nOpen your favourite terminal (Win/Linux/iOS)\n\n\nGo to future project’s path\n\n\nType dotnet new --install Devon4Net.WebAPI.Template\n\n\nType dotnet new Devon4NetAPI\n\n\nGo to project’s path\n\n\nYou are ready to start developing with devon4Net\n\n\n\n\n\nOption 2\n\n\n\nCreate a new dotnet API project from scratch\n\n\nAdd the NuGet package reference to your project\n\n\nType dotnet new --install Devon4Net.WebAPI.Template\n\n\n\n\n\n\n"}